{"ocr_results":[{"text":"第26","box":[[2295,120],[2702,116],[2703,221],[2296,225]]},{"text":"日他们有事富幼阶纵斗争孤实际之作的经","box":[[252,306],[2815,363],[2812,485],[249,428]]},{"text":"作用","box":[[85,351],[303,338],[308,428],[91,441]]},{"text":"验。老千却多苔搬照树付主帮的教身多相信毛","box":[[47,548],[2831,565],[2830,719],[46,702]]},{"text":"兰席今相信群众多正确对待自己刘保持革命的","box":[[54,814],[2822,834],[2821,957],[53,937]]},{"text":"晚节。有些地方双手部的解放，做得还不够","box":[[37,1058],[2687,1073],[2686,1190],[36,1175]]},{"text":"应注意这项工你言新千部应该向老汗部学月","box":[[38,1318],[2845,1328],[2845,1431],[38,1421]]},{"text":"向事像平部学习，积极持他仍的之作言过新","box":[[28,1564],[2842,1559],[2842,1675],[28,1680]]},{"text":"之领导班子要讲团结单队千部、地方彩部","box":[[40,1812],[2852,1807],[2852,1923],[40,1928]]},{"text":"老千都射千部，都要更柏学万立和信任短","box":[[33,2060],[2891,2046],[2892,2179],[34,2193]]},{"text":"三相帮助、互相之持增强在毛泽东思想落","box":[[41,2314],[2881,2282],[2882,2423],[42,2455]]},{"text":"上的团结。各级领导班于都要适照毛主席的教","box":[[30,2552],[2900,2545],[2900,2688],[30,2695]]},{"text":"导今增强九乡阶级觉性开展积极的思您斗争，","box":[[43,2833],[2909,2809],[2910,2937],[44,2961]]},{"text":"开展批与自科批年，团结起来坐爭歌更大的","box":[[54,3084],[2902,3054],[2904,3193],[56,3223]]},{"text":"胜利。，票多晚麦导之费","box":[[68,3312],[1613,3345],[1610,3473],[65,3440]]},{"text":"会上，大家习巡样一个向题为名纵新","box":[[297,3562],[2918,3578],[2917,3752],[296,3736]]},{"text":"的虑多建走后灵怎解他确处理党多会活革要会","box":[[69,3710],[2970,3820],[2960,4095],[58,3988]]},{"text":"原稿无20×16=300","box":[[2125,4019],[2716,4022],[2716,4085],[2125,4081]]}],"dimensions":{"height":4096,"width":3072}}